mkdocs_import_stat_plugin/__init__.py
mkdocs_import_stat_plugin/clear_stat.py
mkdocs_import_stat_plugin/import_stat.py
mkdocs_import_stat_plugin-1.0.5.dist-info/LICENSE
mkdocs_import_stat_plugin-1.0.5.dist-info/METADATA
mkdocs_import_stat_plugin-1.0.5.dist-info/WHEEL
mkdocs_import_stat_plugin-1.0.5.dist-info/entry_points.txt
mkdocs_import_stat_plugin-1.0.5.dist-info/RECORD
