Metadata-Version: 2.3
Name: mkdocs-import-stat-plugin
Version: 1.0.5
Summary: import stat plugin for mkdocs like Markdown Preview Enhanced import
License: MIT
Keywords: mkdocs,markdown,import
Author: q9090960bnb3
Author-email: q9090960bnb3@163.com
Requires-Python: >=3.10,<4.0
Classifier: License :: OSI Approved :: MIT License
Classifier: Programming Language :: Python :: 3
Classifier: Programming Language :: Python :: 3.10
Classifier: Programming Language :: Python :: 3.11
Classifier: Programming Language :: Python :: 3.12
Classifier: Programming Language :: Python :: 3.13
Requires-Dist: mkdocs (>=1.6.1,<2.0.0)
Project-URL: Repository, https://github.com/q9090960bnb3/mkdocs-import-stat-plugin.git
